{
  "id": "866",
  "cache": "/Users/liuzy/MeiZi/数据/866.json",
  "type": "meinv",
  "url": "http://www.177521.com/meinv/866.html",
  "name": "李颖芝爆乳古装造型",
  "img": [
    "/d/file/20141017/kqavydhjbg5.jpg",
    "/d/file/20141017/4uzgm1ndx1y.jpg",
    "/d/file/20141017/ofgl05vlvwz.jpg",
    "/d/file/20141017/5bsr3do5f0o.jpg",
    "/d/file/20141017/zpvczt1x5a2.jpg",
    "/d/file/20141017/4bwc5wyoobf.jpg",
    "/d/file/20141017/c5izvdv2ijg.jpg",
    "/d/file/20141017/txb5nrnev0w.jpg",
    "/d/file/20141017/kqavydhjbg5.jpg",
    "/d/file/20141017/4uzgm1ndx1y.jpg",
    "/d/file/20141017/ofgl05vlvwz.jpg",
    "/d/file/20141017/5bsr3do5f0o.jpg",
    "/d/file/20141017/zpvczt1x5a2.jpg",
    "/d/file/20141017/4bwc5wyoobf.jpg",
    "/d/file/20141017/c5izvdv2ijg.jpg",
    "/d/file/20141017/txb5nrnev0w.jpg"
  ]
}